odoo/addons/connector_infor_account_move/README.rst
odoo/addons/connector_infor_account_move/__init__.py
odoo/addons/connector_infor_account_move/__manifest__.py
odoo/addons/connector_infor_account_move/i18n/connector_infor_account_move.pot
odoo/addons/connector_infor_account_move/i18n/fr.po
odoo/addons/connector_infor_account_move/messages/move.xml.tmpl
odoo/addons/connector_infor_account_move/models/__init__.py
odoo/addons/connector_infor_account_move/models/account_move.py
odoo/addons/connector_infor_account_move/models/infor_account_journal.py
odoo/addons/connector_infor_account_move/models/infor_account_journal_custom_field.py
odoo/addons/connector_infor_account_move/models/infor_backend.py
odoo/addons/connector_infor_account_move/security/ir.model.access.csv
odoo/addons/connector_infor_account_move/static/description/icon.png
odoo/addons/connector_infor_account_move/tests/__init__.py
odoo/addons/connector_infor_account_move/tests/common.py
odoo/addons/connector_infor_account_move/tests/test_account_move.py
odoo/addons/connector_infor_account_move/tests/test_move_messager.py
odoo/addons/connector_infor_account_move/tests/test_move_producer.py
odoo/addons/connector_infor_account_move/tests/examples/move_not_summarized.xml
odoo/addons/connector_infor_account_move/tests/examples/move_not_summarized_currency.xml
odoo/addons/connector_infor_account_move/tests/examples/move_summarized.xml
odoo/addons/connector_infor_account_move/views/account_views.xml
odoo/addons/connector_infor_account_move/views/infor_account_move_views.xml
odoo/addons/connector_infor_account_move/views/infor_backend_views.xml
odoo11_addon_connector_infor_account_move-11.0.1.0.0.99.dev54.dist-info/METADATA
odoo11_addon_connector_infor_account_move-11.0.1.0.0.99.dev54.dist-info/RECORD
odoo11_addon_connector_infor_account_move-11.0.1.0.0.99.dev54.dist-info/WHEEL
odoo11_addon_connector_infor_account_move-11.0.1.0.0.99.dev54.dist-info/top_level.txt
